please/__init__.py
please/cli.py
please/internal/argument.py
please/internal/env.py
please/internal/registertask.py
please/internal/shexec.py
please/internal/taskcontext.py
please/internal/taskfunc.py
please/internal/tasks.py
please/internal/zip.py
please_av1ppp-0.0.7.dist-info/METADATA
please_av1ppp-0.0.7.dist-info/WHEEL
please_av1ppp-0.0.7.dist-info/entry_points.txt
please_av1ppp-0.0.7.dist-info/licenses/LICENSE
please_av1ppp-0.0.7.dist-info/RECORD
