Metadata-Version: 2.4
Name: please_av1ppp
Version: 0.0.7
Summary: Simple task runner
Project-URL: Homepage, https://github.com/av1ppp/please
Project-URL: Issues, https://github.com/av1ppp/please/issues
Author-email: Avi Parampampam <aviparampampam@gmail.com>
License-File: LICENSE
Requires-Python: >=3.8
Requires-Dist: setuptools>=74.1.1
